odoo/addons/disabled_mail_follower_invitation/README.rst
odoo/addons/disabled_mail_follower_invitation/__init__.py
odoo/addons/disabled_mail_follower_invitation/__manifest__.py
odoo/addons/disabled_mail_follower_invitation/static/description/icon.png
odoo/addons/disabled_mail_follower_invitation/wizard/__init__.py
odoo/addons/disabled_mail_follower_invitation/wizard/invitate_followers.py
odoo14_addon_disabled_mail_follower_invitation-14.0.1.0.0.dist-info/METADATA
odoo14_addon_disabled_mail_follower_invitation-14.0.1.0.0.dist-info/WHEEL
odoo14_addon_disabled_mail_follower_invitation-14.0.1.0.0.dist-info/top_level.txt
odoo14_addon_disabled_mail_follower_invitation-14.0.1.0.0.dist-info/RECORD
